Workbook

Sheet Settings
A1: Settings
A2: Change a number here and the whole workbook reprices.
A4: Setting | B4: Value | C4: Why
A5: Filament price per kg | B5: 22 | C5: What you actually pay, delivered
A6: Waste factor | B6: 1.08 | C6: Purge on colour change, skirts, reprints
A7: Machine rate per hour | B7: 2 | C7: Power, wear, nozzles, plates, failures
A8: Labour rate per hour | B8: 30 | C8: What your evening is worth
A9: Packaging per order | B9: 1 | C9: Box, bag, label
A10: Personalisation multiplier | B10: 1.7 | C10: What the name on it is worth
A11: Minimum shipped price | B11: 8 | C11: Below this, postage eats it
A12: Custom job minimum | B12: 30 | C12: No exceptions, ever

Sheet Catalogue
A1: Catalogue
A2: Sort by return per print-hour. Kill anything that has not sold twice.
A4: Product | B4: Grams | C4: Print hrs | D4: Hands-on min | E4: Material | F4: Cost floor | G4: Suggested | H4: List price | I4: Per print-hr | J4: Margin | K4: Notes
A5: Replacement part, custom | B5: 40 | C5: 2 | D5: 25 | E5: =B5*Settings!$B$5/1000*Settings!$B$6 | F5: =E5+C5*Settings!$B$7+D5/60*Settings!$B$8+Settings!$B$9 | G5: =MAX(Settings!$B$11,CEILING(F5*Settings!$B$10,0.5)) | H5: 35 | I5: =IF(C5=0,0,(H5-E5-Settings!$B$9)/C5) | J5: =IF(H5=0,0,(H5-E5-Settings!$B$9)/H5) | K5: Quote per job, 30 EUR minimum
A6: Pet tags x10 | B6: 22 | C6: 1.1 | D6: 10 | E6: =B6*Settings!$B$5/1000*Settings!$B$6 | F6: =E6+C6*Settings!$B$7+D6/60*Settings!$B$8+Settings!$B$9 | G6: =MAX(Settings!$B$11,CEILING(F6*Settings!$B$10,0.5)) | H6: 12 | I6: =IF(C6=0,0,(H6-E6-Settings!$B$9)/C6) | J6: =IF(H6=0,0,(H6-E6-Settings!$B$9)/H6) | K6: PETG if it lives outdoors
A7: Keychains x5 | B7: 28 | C7: 1.4 | D7: 10 | E7: =B7*Settings!$B$5/1000*Settings!$B$6 | F7: =E7+C7*Settings!$B$7+D7/60*Settings!$B$8+Settings!$B$9 | G7: =MAX(Settings!$B$11,CEILING(F7*Settings!$B$10,0.5)) | H7: 14 | I7: =IF(C7=0,0,(H7-E7-Settings!$B$9)/C7) | J7: =IF(H7=0,0,(H7-E7-Settings!$B$9)/H7) | K7: Silk gold letters on matte black
A8: Table numbers x10, logo | B8: 130 | C8: 5.5 | D8: 25 | E8: =B8*Settings!$B$5/1000*Settings!$B$6 | F8: =E8+C8*Settings!$B$7+D8/60*Settings!$B$8+Settings!$B$9 | G8: =MAX(Settings!$B$11,CEILING(F8*Settings!$B$10,0.5)) | H8: 55 | I8: =IF(C8=0,0,(H8-E8-Settings!$B$9)/C8) | J8: =IF(H8=0,0,(H8-E8-Settings!$B$9)/H8) | K8: Venues, weddings, cafes
A9: Two-tone name sign | B9: 45 | C9: 2.3 | D9: 12 | E9: =B9*Settings!$B$5/1000*Settings!$B$6 | F9: =E9+C9*Settings!$B$7+D9/60*Settings!$B$8+Settings!$B$9 | G9: =MAX(Settings!$B$11,CEILING(F9*Settings!$B$10,0.5)) | H9: 22 | I9: =IF(C9=0,0,(H9-E9-Settings!$B$9)/C9) | J9: =IF(H9=0,0,(H9-E9-Settings!$B$9)/H9) | K9: The flagship. One pause.
A10: Ornament set x8 | B10: 70 | C10: 3.4 | D10: 15 | E10: =B10*Settings!$B$5/1000*Settings!$B$6 | F10: =E10+C10*Settings!$B$7+D10/60*Settings!$B$8+Settings!$B$9 | G10: =MAX(Settings!$B$11,CEILING(F10*Settings!$B$10,0.5)) | H10: 28 | I10: =IF(C10=0,0,(H10-E10-Settings!$B$9)/C10) | J10: =IF(H10=0,0,(H10-E10-Settings!$B$9)/H10) | K10: Q4 workhorse, batch the plate
A11: Wall mount | B11: 55 | C11: 2.6 | D11: 8 | E11: =B11*Settings!$B$5/1000*Settings!$B$6 | F11: =E11+C11*Settings!$B$7+D11/60*Settings!$B$8+Settings!$B$9 | G11: =MAX(Settings!$B$11,CEILING(F11*Settings!$B$10,0.5)) | H11: 16 | I11: =IF(C11=0,0,(H11-E11-Settings!$B$9)/C11) | J11: =IF(H11=0,0,(H11-E11-Settings!$B$9)/H11) | K11: Headset, controller, tool
A12: Gridfinity drawer kit x16 | B12: 240 | C12: 9.5 | D12: 15 | E12: =B12*Settings!$B$5/1000*Settings!$B$6 | F12: =E12+C12*Settings!$B$7+D12/60*Settings!$B$8+Settings!$B$9 | G12: =MAX(Settings!$B$11,CEILING(F12*Settings!$B$10,0.5)) | H12: 42 | I12: =IF(C12=0,0,(H12-E12-Settings!$B$9)/C12) | J12: =IF(H12=0,0,(H12-E12-Settings!$B$9)/H12) | K12: Check the licence first
A13: One of each | B13: =SUM(B5:B12) | C13: =SUM(C5:C12) | H13: =SUM(H5:H12)

Sheet Orders
A1: Orders
A2: One row per order. Fill columns A-I and the rest calculates.
A4: Date | B4: Order | C4: Customer | D4: Channel | E4: Product | F4: Qty | G4: Grams total | H4: Print hrs | I4: Price each | J4: Revenue | K4: Material | L4: Fee % | M4: Fee | N4: Profit | O4: Per print-hr | P4: Status | Q4: Due | R4: Notes
J5: =IF(F5="","",F5*I5) | K5: =IF(G5="","",G5*Settings!$B$5/1000*Settings!$B$6) | M5: =IF(J5="","",J5*L5) | N5: =IF(J5="","",J5-K5-M5-Settings!$B$9) | O5: =IF(OR(H5="",H5=0),"",N5/H5)
J6: =IF(F6="","",F6*I6) | K6: =IF(G6="","",G6*Settings!$B$5/1000*Settings!$B$6) | M6: =IF(J6="","",J6*L6) | N6: =IF(J6="","",J6-K6-M6-Settings!$B$9) | O6: =IF(OR(H6="",H6=0),"",N6/H6)
J7: =IF(F7="","",F7*I7) | K7: =IF(G7="","",G7*Settings!$B$5/1000*Settings!$B$6) | M7: =IF(J7="","",J7*L7) | N7: =IF(J7="","",J7-K7-M7-Settings!$B$9) | O7: =IF(OR(H7="",H7=0),"",N7/H7)
J8: =IF(F8="","",F8*I8) | K8: =IF(G8="","",G8*Settings!$B$5/1000*Settings!$B$6) | M8: =IF(J8="","",J8*L8) | N8: =IF(J8="","",J8-K8-M8-Settings!$B$9) | O8: =IF(OR(H8="",H8=0),"",N8/H8)
J9: =IF(F9="","",F9*I9) | K9: =IF(G9="","",G9*Settings!$B$5/1000*Settings!$B$6) | M9: =IF(J9="","",J9*L9) | N9: =IF(J9="","",J9-K9-M9-Settings!$B$9) | O9: =IF(OR(H9="",H9=0),"",N9/H9)
J10: =IF(F10="","",F10*I10) | K10: =IF(G10="","",G10*Settings!$B$5/1000*Settings!$B$6) | M10: =IF(J10="","",J10*L10) | N10: =IF(J10="","",J10-K10-M10-Settings!$B$9) | O10: =IF(OR(H10="",H10=0),"",N10/H10)
J11: =IF(F11="","",F11*I11) | K11: =IF(G11="","",G11*Settings!$B$5/1000*Settings!$B$6) | M11: =IF(J11="","",J11*L11) | N11: =IF(J11="","",J11-K11-M11-Settings!$B$9) | O11: =IF(OR(H11="",H11=0),"",N11/H11)
J12: =IF(F12="","",F12*I12) | K12: =IF(G12="","",G12*Settings!$B$5/1000*Settings!$B$6) | M12: =IF(J12="","",J12*L12) | N12: =IF(J12="","",J12-K12-M12-Settings!$B$9) | O12: =IF(OR(H12="",H12=0),"",N12/H12)
J13: =IF(F13="","",F13*I13) | K13: =IF(G13="","",G13*Settings!$B$5/1000*Settings!$B$6) | M13: =IF(J13="","",J13*L13) | N13: =IF(J13="","",J13-K13-M13-Settings!$B$9) | O13: =IF(OR(H13="",H13=0),"",N13/H13)
J14: =IF(F14="","",F14*I14) | K14: =IF(G14="","",G14*Settings!$B$5/1000*Settings!$B$6) | M14: =IF(J14="","",J14*L14) | N14: =IF(J14="","",J14-K14-M14-Settings!$B$9) | O14: =IF(OR(H14="",H14=0),"",N14/H14)
J15: =IF(F15="","",F15*I15) | K15: =IF(G15="","",G15*Settings!$B$5/1000*Settings!$B$6) | M15: =IF(J15="","",J15*L15) | N15: =IF(J15="","",J15-K15-M15-Settings!$B$9) | O15: =IF(OR(H15="",H15=0),"",N15/H15)
J16: =IF(F16="","",F16*I16) | K16: =IF(G16="","",G16*Settings!$B$5/1000*Settings!$B$6) | M16: =IF(J16="","",J16*L16) | N16: =IF(J16="","",J16-K16-M16-Settings!$B$9) | O16: =IF(OR(H16="",H16=0),"",N16/H16)
... J304: =IF(F304="","",F304*I304) | K304: =IF(G304="","",G304*Settings!$B$5/1000*Settings!$B$6) | M304: =IF(J304="","",J304*L304) | N304: =IF(J304="","",J304-K304-M304-Settings!$B$9) | O304: =IF(OR(H304="",H304=0),"",N304/H304)

Sheet Month
A1: The month
A2: Counts orders by their date. Paid and unpaid alike -- chase the gap.
A4: Month | B4: Orders | C4: Revenue | D4: Material | E4: Fees | F4: Profit | G4: Print hrs | H4: Per print-hr | I4: Target
A5: 2026-09 | B5: =COUNTIFS(Orders!$A$5:$A$304,">="&DATE(2026,9,1),Orders!$A$5:$A$304,"<"&DATE(2026,10,1)) | C5: =SUMIFS(Orders!$J$5:$J$304,Orders!$A$5:$A$304,">="&DATE(2026,9,1),Orders!$A$5:$A$304,"<"&DATE(2026,10,1)) | D5: =SUMIFS(Orders!$K$5:$K$304,Orders!$A$5:$A$304,">="&DATE(2026,9,1),Orders!$A$5:$A$304,"<"&DATE(2026,10,1)) | E5: =SUMIFS(Orders!$M$5:$M$304,Orders!$A$5:$A$304,">="&DATE(2026,9,1),Orders!$A$5:$A$304,"<"&DATE(2026,10,1)) | F5: =SUMIFS(Orders!$N$5:$N$304,Orders!$A$5:$A$304,">="&DATE(2026,9,1),Orders!$A$5:$A$304,"<"&DATE(2026,10,1)) | G5: =SUMIFS(Orders!$H$5:$H$304,Orders!$A$5:$A$304,">="&DATE(2026,9,1),Orders!$A$5:$A$304,"<"&DATE(2026,10,1)) | H5: =IF(G5=0,0,F5/G5) | I5: 200
A6: 2026-10 | B6: =COUNTIFS(Orders!$A$5:$A$304,">="&DATE(2026,10,1),Orders!$A$5:$A$304,"<"&DATE(2026,11,1)) | C6: =SUMIFS(Orders!$J$5:$J$304,Orders!$A$5:$A$304,">="&DATE(2026,10,1),Orders!$A$5:$A$304,"<"&DATE(2026,11,1)) | D6: =SUMIFS(Orders!$K$5:$K$304,Orders!$A$5:$A$304,">="&DATE(2026,10,1),Orders!$A$5:$A$304,"<"&DATE(2026,11,1)) | E6: =SUMIFS(Orders!$M$5:$M$304,Orders!$A$5:$A$304,">="&DATE(2026,10,1),Orders!$A$5:$A$304,"<"&DATE(2026,11,1)) | F6: =SUMIFS(Orders!$N$5:$N$304,Orders!$A$5:$A$304,">="&DATE(2026,10,1),Orders!$A$5:$A$304,"<"&DATE(2026,11,1)) | G6: =SUMIFS(Orders!$H$5:$H$304,Orders!$A$5:$A$304,">="&DATE(2026,10,1),Orders!$A$5:$A$304,"<"&DATE(2026,11,1)) | H6: =IF(G6=0,0,F6/G6) | I6: 400
A7: 2026-11 | B7: =COUNTIFS(Orders!$A$5:$A$304,">="&DATE(2026,11,1),Orders!$A$5:$A$304,"<"&DATE(2026,12,1)) | C7: =SUMIFS(Orders!$J$5:$J$304,Orders!$A$5:$A$304,">="&DATE(2026,11,1),Orders!$A$5:$A$304,"<"&DATE(2026,12,1)) | D7: =SUMIFS(Orders!$K$5:$K$304,Orders!$A$5:$A$304,">="&DATE(2026,11,1),Orders!$A$5:$A$304,"<"&DATE(2026,12,1)) | E7: =SUMIFS(Orders!$M$5:$M$304,Orders!$A$5:$A$304,">="&DATE(2026,11,1),Orders!$A$5:$A$304,"<"&DATE(2026,12,1)) | F7: =SUMIFS(Orders!$N$5:$N$304,Orders!$A$5:$A$304,">="&DATE(2026,11,1),Orders!$A$5:$A$304,"<"&DATE(2026,12,1)) | G7: =SUMIFS(Orders!$H$5:$H$304,Orders!$A$5:$A$304,">="&DATE(2026,11,1),Orders!$A$5:$A$304,"<"&DATE(2026,12,1)) | H7: =IF(G7=0,0,F7/G7) | I7: 700
A8: 2026-12 | B8: =COUNTIFS(Orders!$A$5:$A$304,">="&DATE(2026,12,1),Orders!$A$5:$A$304,"<"&DATE(2027,1,1)) | C8: =SUMIFS(Orders!$J$5:$J$304,Orders!$A$5:$A$304,">="&DATE(2026,12,1),Orders!$A$5:$A$304,"<"&DATE(2027,1,1)) | D8: =SUMIFS(Orders!$K$5:$K$304,Orders!$A$5:$A$304,">="&DATE(2026,12,1),Orders!$A$5:$A$304,"<"&DATE(2027,1,1)) | E8: =SUMIFS(Orders!$M$5:$M$304,Orders!$A$5:$A$304,">="&DATE(2026,12,1),Orders!$A$5:$A$304,"<"&DATE(2027,1,1)) | F8: =SUMIFS(Orders!$N$5:$N$304,Orders!$A$5:$A$304,">="&DATE(2026,12,1),Orders!$A$5:$A$304,"<"&DATE(2027,1,1)) | G8: =SUMIFS(Orders!$H$5:$H$304,Orders!$A$5:$A$304,">="&DATE(2026,12,1),Orders!$A$5:$A$304,"<"&DATE(2027,1,1)) | H8: =IF(G8=0,0,F8/G8) | I8: 1200
A9: 2027-01 | B9: =COUNTIFS(Orders!$A$5:$A$304,">="&DATE(2027,1,1),Orders!$A$5:$A$304,"<"&DATE(2027,2,1)) | C9: =SUMIFS(Orders!$J$5:$J$304,Orders!$A$5:$A$304,">="&DATE(2027,1,1),Orders!$A$5:$A$304,"<"&DATE(2027,2,1)) | D9: =SUMIFS(Orders!$K$5:$K$304,Orders!$A$5:$A$304,">="&DATE(2027,1,1),Orders!$A$5:$A$304,"<"&DATE(2027,2,1)) | E9: =SUMIFS(Orders!$M$5:$M$304,Orders!$A$5:$A$304,">="&DATE(2027,1,1),Orders!$A$5:$A$304,"<"&DATE(2027,2,1)) | F9: =SUMIFS(Orders!$N$5:$N$304,Orders!$A$5:$A$304,">="&DATE(2027,1,1),Orders!$A$5:$A$304,"<"&DATE(2027,2,1)) | G9: =SUMIFS(Orders!$H$5:$H$304,Orders!$A$5:$A$304,">="&DATE(2027,1,1),Orders!$A$5:$A$304,"<"&DATE(2027,2,1)) | H9: =IF(G9=0,0,F9/G9) | I9: 350
A10: 2027-02 | B10: =COUNTIFS(Orders!$A$5:$A$304,">="&DATE(2027,2,1),Orders!$A$5:$A$304,"<"&DATE(2027,3,1)) | C10: =SUMIFS(Orders!$J$5:$J$304,Orders!$A$5:$A$304,">="&DATE(2027,2,1),Orders!$A$5:$A$304,"<"&DATE(2027,3,1)) | D10: =SUMIFS(Orders!$K$5:$K$304,Orders!$A$5:$A$304,">="&DATE(2027,2,1),Orders!$A$5:$A$304,"<"&DATE(2027,3,1)) | E10: =SUMIFS(Orders!$M$5:$M$304,Orders!$A$5:$A$304,">="&DATE(2027,2,1),Orders!$A$5:$A$304,"<"&DATE(2027,3,1)) | F10: =SUMIFS(Orders!$N$5:$N$304,Orders!$A$5:$A$304,">="&DATE(2027,2,1),Orders!$A$5:$A$304,"<"&DATE(2027,3,1)) | G10: =SUMIFS(Orders!$H$5:$H$304,Orders!$A$5:$A$304,">="&DATE(2027,2,1),Orders!$A$5:$A$304,"<"&DATE(2027,3,1)) | H10: =IF(G10=0,0,F10/G10) | I10: 350
A11: Total | B11: =SUM(B5:B10) | C11: =SUM(C5:C10) | D11: =SUM(D5:D10) | E11: =SUM(E5:E10) | F11: =SUM(F5:F10) | G11: =SUM(G5:G10)
A13: If a Q4 month lands under 200 EUR with no repeat customer, change the niche -- not the equipment.
